[
    {
        "chunk_id": 0,
        "start_line": 1,
        "blocks": [
            {
                "type": "html",
                "content": "<blockquote id=\"unknown-user_1740312224999\">inflexion<\/blockquote>\n<div class=\"highlight-unknown-user_1740312224999\"><\/div>\n<br\/>",
                "startLine": 1,
                "lines": [
                    "<blockquote id=\"unknown-user_1740312224999\">inflexion<\/blockquote>",
                    "<div class=\"highlight-unknown-user_1740312224999\"><\/div>",
                    "<br\/>"
                ]
            },
            {
                "type": "html",
                "content": "<blockquote id=\"unknown-user_1740312661016\">and<\/blockquote>\n<div class=\"highlight-unknown-user_1740312661016\"><\/div>\n<br\/>",
                "startLine": 4,
                "lines": [
                    "<blockquote id=\"unknown-user_1740312661016\">and<\/blockquote>",
                    "<div class=\"highlight-unknown-user_1740312661016\"><\/div>",
                    "<br\/>"
                ]
            },
            {
                "type": "html",
                "content": "<blockquote id=\"unknown-user_1740313511020\">Amidst the scramble<\/blockquote>\n<div class=\"highlight-unknown-user_1740313511020\"><\/div>\n<br\/>",
                "startLine": 7,
                "lines": [
                    "<blockquote id=\"unknown-user_1740313511020\">Amidst the scramble<\/blockquote>",
                    "<div class=\"highlight-unknown-user_1740313511020\"><\/div>",
                    "<br\/>"
                ]
            },
            {
                "type": "html",
                "content": "<blockquote id=\"unknown-user_1740313512692\">Amidst the scramble<\/blockquote>\n<div class=\"highlight-unknown-user_1740313512692\"><\/div>\n<br\/>",
                "startLine": 10,
                "lines": [
                    "<blockquote id=\"unknown-user_1740313512692\">Amidst the scramble<\/blockquote>",
                    "<div class=\"highlight-unknown-user_1740313512692\"><\/div>",
                    "<br\/>"
                ]
            },
            {
                "type": "html",
                "content": "<blockquote id=\"unknown-user_1740313520343\">position<\/blockquote>\n<div class=\"highlight-unknown-user_1740313520343\"><\/div>\n<br\/>",
                "startLine": 13,
                "lines": [
                    "<blockquote id=\"unknown-user_1740313520343\">position<\/blockquote>",
                    "<div class=\"highlight-unknown-user_1740313520343\"><\/div>",
                    "<br\/>"
                ]
            },
            {
                "type": "html",
                "content": "<blockquote id=\"unknown-user_1740313568638\">intended<\/blockquote>\n<div class=\"highlight-unknown-user_1740313568638\"><\/div>\n<br\/>",
                "startLine": 16,
                "lines": [
                    "<blockquote id=\"unknown-user_1740313568638\">intended<\/blockquote>",
                    "<div class=\"highlight-unknown-user_1740313568638\"><\/div>",
                    "<br\/>"
                ]
            },
            {
                "type": "html",
                "content": "<blockquote id=\"unknown-user_1740313652029\">could<\/blockquote>\n<div class=\"highlight-unknown-user_1740313652029\"><\/div>\n<br\/>",
                "startLine": 19,
                "lines": [
                    "<blockquote id=\"unknown-user_1740313652029\">could<\/blockquote>",
                    "<div class=\"highlight-unknown-user_1740313652029\"><\/div>",
                    "<br\/>"
                ]
            },
            {
                "type": "html",
                "content": "<blockquote id=\"unknown-user_1740314442720\">into publicly<\/blockquote>\n<div class=\"highlight-unknown-user_1740314442720\"><\/div>\n<br\/>",
                "startLine": 22,
                "lines": [
                    "<blockquote id=\"unknown-user_1740314442720\">into publicly<\/blockquote>",
                    "<div class=\"highlight-unknown-user_1740314442720\"><\/div>",
                    "<br\/>"
                ]
            },
            {
                "type": "html",
                "content": "<blockquote id=\"unknown-user_1740315112484\">lites, was effective. Even when such a position existed only as an idea that had emerged from the unity displayed at the<\/blockquote>\n<div class=\"highlight-unknown-user_1740315112484\"><\/div>\n<br\/>",
                "startLine": 25,
                "lines": [
                    "<blockquote id=\"unknown-user_1740315112484\">lites, was effective. Even when such a position existed only as an idea that had emerged from the unity displayed at the<\/blockquote>",
                    "<div class=\"highlight-unknown-user_1740315112484\"><\/div>",
                    "<br\/>"
                ]
            },
            {
                "type": "html",
                "content": "<blockquote id=\"unknown-user_1740315281351\">Sixth Special Session<\/blockquote>\n<div class=\"highlight-unknown-user_1740315281351\"><\/div>\n<br\/>",
                "startLine": 28,
                "lines": [
                    "<blockquote id=\"unknown-user_1740315281351\">Sixth Special Session<\/blockquote>",
                    "<div class=\"highlight-unknown-user_1740315281351\"><\/div>",
                    "<br\/>"
                ]
            },
            {
                "type": "html",
                "content": "<blockquote id=\"unknown-user_1740315805706\">Solemn Declaration<\/blockquote>\n<div class=\"highlight-unknown-user_1740315805706\"><\/div>\n<br\/>",
                "startLine": 31,
                "lines": [
                    "<blockquote id=\"unknown-user_1740315805706\">Solemn Declaration<\/blockquote>",
                    "<div class=\"highlight-unknown-user_1740315805706\"><\/div>",
                    "<br\/>"
                ]
            },
            {
                "type": "html",
                "content": "<blockquote id=\"unknown-user_1740317355807\">economic<\/blockquote>\n<div class=\"highlight-unknown-user_1740317355807\"><\/div>\n<br\/>",
                "startLine": 34,
                "lines": [
                    "<blockquote id=\"unknown-user_1740317355807\">economic<\/blockquote>",
                    "<div class=\"highlight-unknown-user_1740317355807\"><\/div>",
                    "<br\/>"
                ]
            },
            {
                "type": "html",
                "content": "<blockquote id=\"unknown-user_1740351343770\">Determining<\/blockquote>\n<div class=\"highlight-unknown-user_1740351343770\"><\/div>\n<br\/>",
                "startLine": 37,
                "lines": [
                    "<blockquote id=\"unknown-user_1740351343770\">Determining<\/blockquote>",
                    "<div class=\"highlight-unknown-user_1740351343770\"><\/div>",
                    "<br\/>"
                ]
            },
            {
                "type": "html",
                "content": "<blockquote id=\"unknown-user_1740351853259\">brought<\/blockquote>\n<div class=\"highlight-unknown-user_1740351853259\"><\/div>\n<br\/>",
                "startLine": 40,
                "lines": [
                    "<blockquote id=\"unknown-user_1740351853259\">brought<\/blockquote>",
                    "<div class=\"highlight-unknown-user_1740351853259\"><\/div>",
                    "<br\/>"
                ]
            },
            {
                "type": "html",
                "content": "<blockquote id=\"unknown-user_1741668260901\">had<\/blockquote>\n<div class=\"highlight-unknown-user_1741668260901\"><\/div>\n<br\/>",
                "startLine": 43,
                "lines": [
                    "<blockquote id=\"unknown-user_1741668260901\">had<\/blockquote>",
                    "<div class=\"highlight-unknown-user_1741668260901\"><\/div>",
                    "<br\/>"
                ]
            },
            {
                "type": "html",
                "content": "<blockquote id=\"unknown-user_1741669068412\">G77<\/blockquote>\n<div class=\"highlight-unknown-user_1741669068412\"><\/div>\n<br\/>",
                "startLine": 46,
                "lines": [
                    "<blockquote id=\"unknown-user_1741669068412\">G77<\/blockquote>",
                    "<div class=\"highlight-unknown-user_1741669068412\"><\/div>",
                    "<br\/>"
                ]
            },
            {
                "type": "html",
                "content": "<blockquote id=\"unknown-user_1741670810804\">in the future<\/blockquote>\n<div class=\"highlight-unknown-user_1741670810804\"><\/div>\n<br\/>",
                "startLine": 49,
                "lines": [
                    "<blockquote id=\"unknown-user_1741670810804\">in the future<\/blockquote>",
                    "<div class=\"highlight-unknown-user_1741670810804\"><\/div>",
                    "<br\/>"
                ]
            },
            {
                "type": "html",
                "content": "<blockquote id=\"user-name_1738731387734\">dddd<\/blockquote>\n<div class=\"highlight-user-name_1738731387734\"><\/div>\n<br\/>",
                "startLine": 52,
                "lines": [
                    "<blockquote id=\"user-name_1738731387734\">dddd<\/blockquote>",
                    "<div class=\"highlight-user-name_1738731387734\"><\/div>",
                    "<br\/>"
                ]
            },
            {
                "type": "html",
                "content": "<blockquote id=\"unknown-user_1741670872844\">A Moment of Possibility<\/blockquote>\n<div class=\"highlight-unknown-user_1741670872844\"><\/div>\n<br\/>",
                "startLine": 55,
                "lines": [
                    "<blockquote id=\"unknown-user_1741670872844\">A Moment of Possibility<\/blockquote>",
                    "<div class=\"highlight-unknown-user_1741670872844\"><\/div>",
                    "<br\/>"
                ]
            },
            {
                "type": "html",
                "content": "<blockquote id=\"unknown-user_1739148302394\">lt of the inadequate power of its underlying strategy, has not been disproven, moves to reassess this assumption were commenced by the Marxist historian Vijay Prashad. Before Pr<\/blockquote>\n<div class=\"highlight-unknown-user_1739148302394\"><\/div>\n<br\/>",
                "startLine": 58,
                "lines": [
                    "<blockquote id=\"unknown-user_1739148302394\">lt of the inadequate power of its underlying strategy, has not been disproven, moves to reassess this assumption were commenced by the Marxist historian Vijay Prashad. Before Pr<\/blockquote>",
                    "<div class=\"highlight-unknown-user_1739148302394\"><\/div>",
                    "<br\/>"
                ]
            },
            {
                "type": "html",
                "content": "<blockquote id=\"unknown-user_1739255206024\">New International Economic Order<\/blockquote>\n<div class=\"highlight-unknown-user_1739255206024\"><\/div>\n<br\/>",
                "startLine": 61,
                "lines": [
                    "<blockquote id=\"unknown-user_1739255206024\">New International Economic Order<\/blockquote>",
                    "<div class=\"highlight-unknown-user_1739255206024\"><\/div>",
                    "<br\/>"
                ]
            },
            {
                "type": "html",
                "content": "<blockquote id=\"unknown-user_1739318330595\">political<\/blockquote>\n<div class=\"highlight-unknown-user_1739318330595\"><\/div>\n<br\/>",
                "startLine": 64,
                "lines": [
                    "<blockquote id=\"unknown-user_1739318330595\">political<\/blockquote>",
                    "<div class=\"highlight-unknown-user_1739318330595\"><\/div>",
                    "<br\/>"
                ]
            },
            {
                "type": "html",
                "content": "<blockquote id=\"unknown-user_1739838329539\">NIEO<\/blockquote>\n<div class=\"highlight-unknown-user_1739838329539\"><\/div>\n<br\/>",
                "startLine": 67,
                "lines": [
                    "<blockquote id=\"unknown-user_1739838329539\">NIEO<\/blockquote>",
                    "<div class=\"highlight-unknown-user_1739838329539\"><\/div>",
                    "<br\/>"
                ]
            },
            {
                "type": "html",
                "content": "<blockquote id=\"unknown-user_1739318767231\">overview<\/blockquote>\n<div class=\"highlight-unknown-user_1739318767231\"><\/div>\n<br\/>",
                "startLine": 70,
                "lines": [
                    "<blockquote id=\"unknown-user_1739318767231\">overview<\/blockquote>",
                    "<div class=\"highlight-unknown-user_1739318767231\"><\/div>",
                    "<br\/>"
                ]
            },
            {
                "type": "html",
                "content": "<blockquote id=\"unknown-user_1739148344805\">international law<\/blockquote>\n<div class=\"highlight-unknown-user_1739148344805\"><\/div>\n<br\/>",
                "startLine": 73,
                "lines": [
                    "<blockquote id=\"unknown-user_1739148344805\">international law<\/blockquote>",
                    "<div class=\"highlight-unknown-user_1739148344805\"><\/div>",
                    "<br\/>"
                ]
            },
            {
                "type": "html",
                "content": "<blockquote id=\"unknown-user_1738804253931\">Eric Helleiner<\/blockquote>\n<div class=\"highlight-unknown-user_1738804253931\"><\/div>\n<br\/>",
                "startLine": 76,
                "lines": [
                    "<blockquote id=\"unknown-user_1738804253931\">Eric Helleiner<\/blockquote>",
                    "<div class=\"highlight-unknown-user_1738804253931\"><\/div>",
                    "<br\/>"
                ]
            },
            {
                "type": "html",
                "content": "<blockquote id=\"user-name_1738367084769\">that potentially<\/blockquote>\n<div class=\"highlight-user-name_1738367084769\"><\/div>\n<br\/>",
                "startLine": 79,
                "lines": [
                    "<blockquote id=\"user-name_1738367084769\">that potentially<\/blockquote>",
                    "<div class=\"highlight-user-name_1738367084769\"><\/div>",
                    "<br\/>"
                ]
            },
            {
                "type": "html",
                "content": "<blockquote id=\"user-name_1738193363001\">order<\/blockquote>\n<div class=\"highlight-user-name_1738193363001\"><\/div>\n<br\/>",
                "startLine": 82,
                "lines": [
                    "<blockquote id=\"user-name_1738193363001\">order<\/blockquote>",
                    "<div class=\"highlight-user-name_1738193363001\"><\/div>",
                    "<br\/>"
                ]
            },
            {
                "type": "html",
                "content": "<blockquote id=\"user-name_1738192811790\">This is important because it shows how the three core concepts that formed the basis of the Third World Project<\/blockquote>\n<div class=\"highlight-user-name_1738192811790\"><\/div>\n<br\/>",
                "startLine": 85,
                "lines": [
                    "<blockquote id=\"user-name_1738192811790\">This is important because it shows how the three core concepts that formed the basis of the Third World Project<\/blockquote>",
                    "<div class=\"highlight-user-name_1738192811790\"><\/div>",
                    "<br\/>"
                ]
            },
            {
                "type": "html",
                "content": "<blockquote id=\"unknown-user_1741662062985\">and the success<\/blockquote>\n<div class=\"highlight-unknown-user_1741662062985\"><\/div>\n<br\/>",
                "startLine": 88,
                "lines": [
                    "<blockquote id=\"unknown-user_1741662062985\">and the success<\/blockquote>",
                    "<div class=\"highlight-unknown-user_1741662062985\"><\/div>",
                    "<br\/>"
                ]
            },
            {
                "type": "html",
                "content": "<blockquote id=\"unknown-user_1739319741394\">more directly<\/blockquote>\n<div class=\"highlight-unknown-user_1739319741394\"><\/div>\n<br\/>",
                "startLine": 91,
                "lines": [
                    "<blockquote id=\"unknown-user_1739319741394\">more directly<\/blockquote>",
                    "<div class=\"highlight-unknown-user_1739319741394\"><\/div>",
                    "<br\/>"
                ]
            },
            {
                "type": "html",
                "content": "<blockquote id=\"user-name_1738651476567\">timely transfer<\/blockquote>\n<div class=\"highlight-user-name_1738651476567\"><\/div>\n<br\/>",
                "startLine": 94,
                "lines": [
                    "<blockquote id=\"user-name_1738651476567\">timely transfer<\/blockquote>",
                    "<div class=\"highlight-user-name_1738651476567\"><\/div>",
                    "<br\/>"
                ]
            },
            {
                "type": "html",
                "content": "<blockquote id=\"unknown-user_1740353668773\">Solemn Declaration<\/blockquote>\n<div class=\"highlight-unknown-user_1740353668773\"><\/div>\n<br\/>",
                "startLine": 97,
                "lines": [
                    "<blockquote id=\"unknown-user_1740353668773\">Solemn Declaration<\/blockquote>",
                    "<div class=\"highlight-unknown-user_1740353668773\"><\/div>",
                    "<br\/>"
                ]
            }
        ],
        "end_line": 99
    },
    {
        "chunk_id": 1,
        "start_line": 100,
        "blocks": [
            {
                "type": "html",
                "content": "<blockquote id=\"unknown-user_1740359317227\">Special<\/blockquote>\n<div class=\"highlight-unknown-user_1740359317227\"><\/div>\n<br\/>",
                "startLine": 100,
                "lines": [
                    "<blockquote id=\"unknown-user_1740359317227\">Special<\/blockquote>",
                    "<div class=\"highlight-unknown-user_1740359317227\"><\/div>",
                    "<br\/>"
                ]
            },
            {
                "type": "html",
                "content": "<blockquote id=\"unknown-user_1740354118859\">Venezuela<\/blockquote>\n<div class=\"highlight-unknown-user_1740354118859\"><\/div>\n<br\/>",
                "startLine": 103,
                "lines": [
                    "<blockquote id=\"unknown-user_1740354118859\">Venezuela<\/blockquote>",
                    "<div class=\"highlight-unknown-user_1740354118859\"><\/div>",
                    "<br\/>"
                ]
            },
            {
                "type": "html",
                "content": "<blockquote id=\"unknown-user_1738908900842\">Karin Lissakers raises two important points. Firstly, she notes that a \u2018divide-and-rule tactic\u2019 on behalf of creditors was \u2018helped by timing.\u2019[^474] That is, because the debtors did not \u2018experience their most acute payments problems simultaneously\u2019, banks \u2018could settle with one large de<\/blockquote>\n<div class=\"highlight-unknown-user_1738908900842\"><\/div>\n<br\/>",
                "startLine": 106,
                "lines": [
                    "<blockquote id=\"unknown-user_1738908900842\">Karin Lissakers raises two important points. Firstly, she notes that a \u2018divide-and-rule tactic\u2019 on behalf of creditors was \u2018helped by timing.\u2019[^474] That is, because the debtors did not \u2018experience their most acute payments problems simultaneously\u2019, banks \u2018could settle with one large de<\/blockquote>",
                    "<div class=\"highlight-unknown-user_1738908900842\"><\/div>",
                    "<br\/>"
                ]
            },
            {
                "type": "html",
                "content": "<blockquote id=\"unknown-user_1740311177472\">plan<\/blockquote>\n<div class=\"highlight-unknown-user_1740311177472\"><\/div>\n<br\/>",
                "startLine": 109,
                "lines": [
                    "<blockquote id=\"unknown-user_1740311177472\">plan<\/blockquote>",
                    "<div class=\"highlight-unknown-user_1740311177472\"><\/div>",
                    "<br\/>"
                ]
            },
            {
                "type": "html",
                "content": "<blockquote id=\"unknown-user_1739844290250\">mp<\/blockquote>\n<div class=\"highlight-unknown-user_1739844290250\"><\/div>\n<br\/>",
                "startLine": 112,
                "lines": [
                    "<blockquote id=\"unknown-user_1739844290250\">mp<\/blockquote>",
                    "<div class=\"highlight-unknown-user_1739844290250\"><\/div>",
                    "<br\/>"
                ]
            },
            {
                "type": "html",
                "content": "<blockquote id=\"unknown-user_1739255315140\">aftermath of the NIEO Project<\/blockquote>\n<div class=\"highlight-unknown-user_1739255315140\"><\/div>\n<br\/>",
                "startLine": 115,
                "lines": [
                    "<blockquote id=\"unknown-user_1739255315140\">aftermath of the NIEO Project<\/blockquote>",
                    "<div class=\"highlight-unknown-user_1739255315140\"><\/div>",
                    "<br\/>"
                ]
            }
        ],
        "end_line": 117
    }
]